README.rst
setup.py
AVISO.egg-info/PKG-INFO
AVISO.egg-info/SOURCES.txt
AVISO.egg-info/dependency_links.txt
AVISO.egg-info/entry_points.txt
AVISO.egg-info/requires.txt
AVISO.egg-info/top_level.txt
AVISO.egg-info/zip-safe
aviso/__init__.py
aviso/aviso.py
aviso/extra.py
aviso/topex.py
bin/AVISO_download