Metadata-Version: 1.1
Name: AVISO
Version: 0.9.2
Summary: A library to handle altimetric data produced by AVISO
Home-page: https://pyaviso.castelao.net
Author: Guilherme Castelao
Author-email: guilherme@castelao.net
License: MIT
Keywords: altimetry,AVISO,TOPEX,JASON,oceanography,Sea Surface Height
Platform: any
Classifier: Development Status :: 4 - Beta
Classifier: Environment :: Console
Classifier: Intended Audience :: Science/Research
Classifier: Intended Audience :: Developers
Classifier: License :: OSI Approved :: MIT License 
Classifier: Operating System :: OS Independent
Classifier: Programming Language :: Python :: 2.6
Classifier: Programming Language :: Python :: 2.7
Classifier: Topic :: Scientific/Engineering
Classifier: Topic :: Software Development :: Libraries :: Python Modules
